mkdocs_macros_include_from_url/__init__.py
mkdocs_macros_include_from_url-0.1.0.dist-info/METADATA
mkdocs_macros_include_from_url-0.1.0.dist-info/WHEEL
mkdocs_macros_include_from_url-0.1.0.dist-info/top_level.txt
mkdocs_macros_include_from_url-0.1.0.dist-info/RECORD
