Metadata-Version: 2.4
Name: mkdocs-macros-include-from-url
Version: 0.1.0
Summary: MkDocs Macros Plugin - Include content from URL
Author: Landry JUGE
License: MIT
Dynamic: author
Dynamic: license
Dynamic: summary
